{
    "name": "",
    "CardType": "",
    "CardLimit": "",
    "Description": "",
    "requires": [
        ""
    ],
    "requiresEvent": [
        {
            "NameOfEvent": "",
            "Progress": "99",
            "ChoiceNumber": "-1",
            "Choice": ""
        }
    ],
    "Speakers": [
        {
            "name": "",
            "postName": "",
            "SpeakerType": ""
        }
    ],
    "EventText": [
        {
            "NameOfScene": "",
            "theScene": [
                ""
            ]
        }
    ]
}