{
    "name": "Kotone's Hypno Slave",
    "description": "Te has convertido en el esclavo hipnotizado de Kotone, completamente cautivado con la sensación de ser puesto en trances hipnóticos, disminuyendo tu trance Res en un 20%.Pero ganó un 5% de reses contra el sueño y el encanto, 3 fuerza de voluntad y 20 excitación máxima.Cuando está afectado por Trance, comienza el mostrador en las 5 en lugar de las 10, ya no comienza a salir de su trance de forma natural y tiene que confiar en los artículos para escapar, y tiene una posibilidad adicional del 10% de perder su turno si está completamentefascinado.También ganaste 10 fetiche en besos, senos, culo, piernas, pies y monstruosos.",
    "LevelReq": "0",
    "PerkReq": [
        ""
    ],
    "StatReq": [
        ""
    ],
    "StatReqAmount": [
        "0"
    ],
    "PerkType": [
        "StartDeeperInTrance",
        "CantBreakFreeOfTranceWithoutItems",
        "TranceStunChance",
        "GainArousal",
        "Willpower",
        "TranceRes",
        "SleepRes",
        "CharmRes",
        "IncreaseFetish",
        "IncreaseFetish",
        "IncreaseFetish",
        "IncreaseFetish",
        "IncreaseFetish",
        "IncreaseFetish",
        "IncreaseFetish"
    ],
    "EffectPower": [
        "5",
        "0",
        "10",
        "20",
        "3",
        "-20",
        "5",
        "5",
        "HypnosisAddict|/|50",
        "Kissing|/|10",
        "Breasts|/|10",
        "Ass|/|10",
        "Legs|/|10",
        "Feet|/|10",
        "Monstrous|/|10"
    ],
    "PlayerCanPurchase": "No"
}