{
    "name": "Vili's Puff Puff Massage",
    "cost": "5",
    "costType": "ep",
    "requiredLevel": "0",
    "learningCost": "0",
    "skillType": "attack",
    "statType": "Allure",
    "requiredStat": "7",
    "skillTags": [
        "Seduction"
    ],
    "fetishTags": [
        "Breasts",
        "Vili's Curse"
    ],
    "startsStance": "",
    "requiresStance": "Breast Smother",
    "unusableIfStance": [
        "Titfuck",
        "Blowjob",
        "Making Out"
    ],
    "requiresTargetStance": [
        "Any"
    ],
    "unusableIfTargetHasTheseSets": [
        [
            "Breast Smother",
            "Breast Smother"
        ]
    ],
    "unusableIfTarget": [
        ""
    ],
    "removesStance": "None",
    "requiresStatusEffect": "None",
    "requiresStatusPotency": "0",
    "unusableIfStatusEffect": [
        "None"
    ],
    "power": "30",
    "minRange": "90",
    "maxRange": "110",
    "recoil": "0",
    "targetType": "single",
    "statusEffect": "Charm",
    "statusChance": "50",
    "statusDuration": "6",
    "statusPotency": "0",
    "statusResistedBy": "Willpower",
    "statusText": "",
    "descrip": "",
    "outcome": "[AttackerName] gira suavemente sus grandes tetas suaves alrededor de la cara de [TargetName] en los círculos alternativos, dejando [TargetHisOrHer] la mente girando con excitación mientras su abundante escote se derrite [TargetHisOrHer] resistencia.",
    "miss": "[AttackerName] gira suavemente sus grandes tetas suaves alrededor de la cara de [TargetName] en círculos alternos, ¡pero [TargetName] logra ignorar las sensaciones agradables!",
    "statusOutcome": "[TargetName] no puedo evitar estar encantado por la sensación de las tetas perfectas de [AttackerName] masajeando su rostro![TargetName] está encantado!",
    "statusMiss": "",
    "restraintStruggle": "",
    "restraintStruggleCharmed": "",
    "restraintEscaped": "",
    "restraintEscapedFail": ""
}