{
    "name": "AphroGridTimers",
    "CardType": "Event",
    "CardLimit": "0",
    "Description": "",
    "requires": [
        ""
    ],
    "Speakers": [
        {
            "name": "Ceris",
            "postName": "",
            "SpeakerType": "Monster"
        }
    ],
    "EventText": [
        {
            "NameOfScene": "AphroTimer",
            "theScene": [
                "IfChoice",
                "1",
                "",
                "DormantGridTimer",
                "IfChoice",
                "1",
                "Warning",
                "WarningGridTimer",
                "IfChoice",
                "1",
                "Active",
                "ActiveGridTimer",
                "IfChoice",
                "1",
                "Calming",
                "CalmingGridTimer"
            ]
        },
        {
            "NameOfScene": "DormantGridTimer",
            "theScene": [
                "ChangeProgress",
                "1",
                "IfProgressEqualsOrGreater",
                "5",
                "DormantGridTimeUp"
            ]
        },
        {
            "NameOfScene": "DormantGridTimeUp",
            "theScene": [
                "SetProgress",
                "0",
                "SetChoice",
                "1",
                "Warning"
            ]
        },
        {
            "NameOfScene": "SwapToWarning",
            "theScene": [
                "SpawnGridNPC",
                "AphroGridWarning",
                "Here",
                "RemoveGridNPC",
                "Current"
            ]
        },
        {
            "NameOfScene": "WarningGridTimer",
            "theScene": [
                "ChangeProgress",
                "1",
                "IfProgressEqualsOrGreater",
                "2",
                "WarningTimerUp"
            ]
        },
        {
            "NameOfScene": "WarningTimerUp",
            "theScene": [
                "SetProgress",
                "0",
                "SetChoice",
                "1",
                "Active"
            ]
        },
        {
            "NameOfScene": "SwapToActive",
            "theScene": [
                "SpawnGridNPC",
                "AphroGridActive",
                "Here",
                "RemoveGridNPC",
                "Current"
            ]
        },
        {
            "NameOfScene": "ActiveGridTimer",
            "theScene": [
                "ChangeProgress",
                "1",
                "IfProgressEqualsOrGreater",
                "8",
                "ActiveTimerUp"
            ]
        },
        {
            "NameOfScene": "ActiveTimerUp",
            "theScene": [
                "SetProgress",
                "0",
                "SetChoice",
                "1",
                "Calming"
            ]
        },
        {
            "NameOfScene": "SwapToCalm",
            "theScene": [
                "SpawnGridNPC",
                "AphroGridCalming",
                "Here",
                "RemoveGridNPC",
                "Current"
            ]
        },
        {
            "NameOfScene": "CalmingGridTimer",
            "theScene": [
                "ChangeProgress",
                "1",
                "IfProgressEqualsOrGreater",
                "3",
                "CalmTimerUp"
            ]
        },
        {
            "NameOfScene": "CalmTimerUp",
            "theScene": [
                "SetProgress",
                "0",
                "SetChoice",
                "1",
                ""
            ]
        },
        {
            "NameOfScene": "SwapToDormant",
            "theScene": [
                "SpawnGridNPC",
                "AphroGridDormant",
                "Here",
                "RemoveGridNPC",
                "Current"
            ]
        },
        {
            "NameOfScene": "StepOnAphroGrid",
            "theScene": [
                "IfGridPlayerStunned",
                "Nothing",
                "PlaySoundEffect",
                "sfx/Magic/steam01.mp3",
                "ApplyStatusEffect",
                "AhproGridTrigger",
                "IfPlayerOrgasm",
                "Too much aphrodisiac",
                "IfPlayerHasStatusEffectWithPotencyEqualOrGreater",
                "Aphrodisiac",
                "100",
                "Too much aphrodisiac"
            ]
        },
        {
            "NameOfScene": "Too much aphrodisiac",
            "theScene": [
                "A medida que la bruma fluida de los afrodisíacos llena sus sentidos sobreestimulados, dejas escapar un gemido bajo y aturdido, tus piernas temblan por un momento mientras montas un placer vertiginoso en lo alto, tu polla se mueve y palpitando con emoción.",
                "Incapaz de retenerte más atrás, sacas tu eje rígido libre y lo acaricia rápidamente mientras respiras fuertes del aire teñido de púrpura, indiferente de quién o qué puede estar a tu alrededor.Desesperadamente, bombea su erección necesitada en busca de liberación, cada razón se erosiona con la lujuria.",
                "PlayerOrgasm",
                "1",
                "StunGridPlayer",
                "1",
                "GetEventAndSetChoice",
                "BlackHeartTile",
                "1",
                "",
                "CallSceneThenReturn",
                "CheckSpirit",
                "Solicitándose, sigues acariciándote y agitándote las caderas hasta llegar a un clímax tembloroso, brotando largas cuerdas de semillas por todo el piso del laberinto, tus piernas temblorosas casi dando la cascada de la dicha orgásmica corriendo a través de ti, dejándote jadeandoEn más de la neblina afrodisíaca antes de recordarte completamente, aturdido pero aliviado por tu sesión de fapping inducida por drogas."
            ]
        },
        {
            "NameOfScene": "CheckSpirit",
            "theScene": [
                "IfPlayerSpiritGone",
                "RestoreOneSpirit"
            ]
        },
        {
            "NameOfScene": "RestoreOneSpirit",
            "theScene": [
                "SetSpirit",
                "1"
            ]
        },
        {
            "NameOfScene": "Nothing",
            "theScene": []
        },
        {
            "NameOfScene": "EventBreak",
            "theScene": [
                "Evento Broko"
            ]
        }
    ]
}