{
    "name": "Perverting Entangling Temptation",
    "cost": "5",
    "costType": "ep",
    "requiredLevel": "0",
    "learningCost": "0",
    "skillType": "attack",
    "statType": "Allure",
    "requiredStat": "0",
    "skillTags": [
        "Sex",
        "Unholy"
    ],
    "fetishTags": [
        "Penetration"
    ],
    "startsStance": "",
    "requiresStance": "Penetration",
    "unusableIfStance": [
        ""
    ],
    "requiresTargetStance": [
        "Penetration",
        "Slimed 100%"
    ],
    "unusableIfTarget": [
        ""
    ],
    "removesStance": "None",
    "requiresStatusEffect": "None",
    "requiresStatusPotency": "0",
    "unusableIfStatusEffect": [
        "None"
    ],
    "power": "60",
    "minRange": "90",
    "maxRange": "110",
    "recoil": "5",
    "targetType": "single",
    "statusEffect": "Charm",
    "statusChance": "150",
    "statusDuration": "11",
    "statusPotency": "0",
    "statusResistedBy": "Willpower",
    "statusText": "",
    "descrip": "",
    "outcome": "Ahora que estás completamente envuelto en las formas pegajosas de las perpetuas, la tentadora púrpura se dirige hacia ti, sus tendientes de cabello que enredan tus brazos para obligar a tus manos a apretar su culo regordete, cada columpio hacia abajo de su cintura enviando un pulso ondulante de impíaEuphoria a través de todo su cuerpo mientras la vista obscena de su culo que se mueve tiene su mirada agregada., hay poco que puedas hacer, pero tambaleándose las caderas con el tiempo con el limo morado morado que coos y se ríe malvadamente mientras te hundes más y más profundamente en su control seductor en medio de los impactos húmedos de Jellowy del sexo.",
    "miss": "Ahora que estás completamente envuelto en las formas pegajosas de los perpetuas, la tentrés púrpura se aleja de ti, sus tendidos en el cabello alcanzan posesivamente tus brazos, ¡pero te las arreglas para evadir su agarre de lazo!",
    "statusOutcome": "|f|CallCombatEventAndScene|/|DarkPerpetuaCombatEvent|/|DepravedEntanglingCharm|n|",
    "statusMiss": "",
    "restraintStruggle": "",
    "restraintStruggleCharmed": "",
    "restraintEscaped": "",
    "restraintEscapedFail": ""
}